deepdraw/__init__.py
deepdraw/configs/__init__.py
deepdraw/configs/datasets/__init__.py
deepdraw/configs/datasets/csv.py
deepdraw/configs/datasets/avdrive/__init__.py
deepdraw/configs/datasets/avdrive/default.py
deepdraw/configs/datasets/chasedb1/__init__.py
deepdraw/configs/datasets/chasedb1/covd.py
deepdraw/configs/datasets/chasedb1/first_annotator.py
deepdraw/configs/datasets/chasedb1/first_annotator_1024.py
deepdraw/configs/datasets/chasedb1/first_annotator_768.py
deepdraw/configs/datasets/chasedb1/mtest.py
deepdraw/configs/datasets/chasedb1/second_annotator.py
deepdraw/configs/datasets/chasedb1/xtest.py
deepdraw/configs/datasets/combined/__init__.py
deepdraw/configs/datasets/combined/oc.py
deepdraw/configs/datasets/combined/od.py
deepdraw/configs/datasets/combined/vessel.py
deepdraw/configs/datasets/cxr8/__init__.py
deepdraw/configs/datasets/cxr8/default.py
deepdraw/configs/datasets/cxr8/default_gtcrop.py
deepdraw/configs/datasets/cxr8/gt_xtest.py
deepdraw/configs/datasets/cxr8/xtest.py
deepdraw/configs/datasets/drhagis/__init__.py
deepdraw/configs/datasets/drhagis/default.py
deepdraw/configs/datasets/drionsdb/__init__.py
deepdraw/configs/datasets/drionsdb/expert1.py
deepdraw/configs/datasets/drionsdb/expert1_512.py
deepdraw/configs/datasets/drionsdb/expert1_768.py
deepdraw/configs/datasets/drionsdb/expert2.py
deepdraw/configs/datasets/drionsdb/expert2_512.py
deepdraw/configs/datasets/drionsdb/expert2_768.py
deepdraw/configs/datasets/drishtigs1/__init__.py
deepdraw/configs/datasets/drishtigs1/cup_all.py
deepdraw/configs/datasets/drishtigs1/cup_all_512.py
deepdraw/configs/datasets/drishtigs1/cup_all_768.py
deepdraw/configs/datasets/drishtigs1/cup_any.py
deepdraw/configs/datasets/drishtigs1/disc_all.py
deepdraw/configs/datasets/drishtigs1/disc_all_512.py
deepdraw/configs/datasets/drishtigs1/disc_all_768.py
deepdraw/configs/datasets/drishtigs1/disc_any.py
deepdraw/configs/datasets/drive/__init__.py
deepdraw/configs/datasets/drive/covd.py
deepdraw-1.5.0.dist-info/METADATA
deepdraw-1.5.0.dist-info/WHEEL
deepdraw-1.5.0.dist-info/entry_points.txt
deepdraw-1.5.0.dist-info/top_level.txt
deepdraw-1.5.0.dist-info/zip-safe
deepdraw-1.5.0.dist-info/RECORD
